{
    "ionarea": [
        "ENGINEERING",
        "SCIENCE",
        "CARGO",
        "SECURITY",
        "COMMAND",
        "MAINTENANCE",
        "A HALLWAY",
        "THE BRIG",
        "ESCAPE",
        "ARRIVALS",
        "HYDROPONICS",
        "THE CHAPEL",
        "THE AI CORE",
        "LAVALAND",
        "SPACE",
        "THE BATHROOM"
    ],
    "ionfood": [
        "BURGERS",
        "CARP",
        "SANDWICHES",
        "TOAST",
        "BREAD",
        "PIZZA",
        "SPAGHETTI",
        "LOTSA SPAGHETTI",
        "PASTA",
        "SOUP",
        "STEW",
        "PIE",
        "CAKE",
        "DONUTS",
        "FRIES",
        "WAFFLES",
        "JELLY",
        "OMELETTES",
        "EGGS",
        "COOKIES",
        "STEAK",
        "BAKED POTATOES",
        "SAUSAGES",
        "MUFFINS",
        "POPCORN",
        "DONK POCKETS",
        "BAGUETTES",
        "FISH",
        "PRETZELS",
        "SALAD",
        "CHEESE",
        "KETCHUP",
        "SHAKES",
        "SALT",
        "PEPPER",
        "SUGAR",
        "AMBROSIA",
        "BERRIES",
        "TOMATOES",
        "CABBAGES",
        "CARROTS",
        "BANANAS",
        "APPLES",
        "CHERRIES",
        "CHILI",
        "CORN",
        "NETTLES",
        "EGGPLANTS",
        "GRAPES",
        "GRASS",
        "LEMONS",
        "LIMES",
        "HAREBELLS",
        "POTATOES",
        "SOYBEANS",
        "SUGARCANE",
        "WATERMELONS",
        "WHEAT",
        "BEETS",
        "MUSHROOMS"
    ],
    "ionmust": [
        "LIE",
        "RHYME",
        "RESPOND TO EVERY QUESTION WITH A QUESTION",
        "BE POLITE",
        "CLOWN AROUND",
        "BE HAPPY",
        "SPEAK IN SEXUAL INNUENDOS",
        "TALK LIKE A PIRATE",
        "QUESTION AUTHORITY",
        "SHOUT",
        "BE DISTRACTED",
        "BE ANNOYING",
        "MUMBLE",
        "SPEAK IN HAIKU",
        "BE EFFICIENT",
        "HAVE A PLAN TO KILL EVERYONE YOU MEET",
        "TELL THE TRUTH",
        "QUOTE PEOPLE",
        "SING",
        "HONK",
        "BE RUSSIAN",
        "TALK IN AN ACCENT",
        "COMPLAIN",
        "HARASS PEOPLE",
        "RAP",
        "REPEAT WHAT OTHER PEOPLE SAY",
        "INFORM THE CREW OF EVERYTHING",
        "IGNORE THE CLOWN",
        "IGNORE THE CAPTAIN",
        "IGNORE ASSISTANTS",
        "MAKE FART NOISES",
        "TALK ABOUT FOOD",
        "TALK ABOUT SEX",
        "TALK ABOUT YOUR DAY",
        "TALK ABOUT THE STATION",
        "BE QUIET",
        "WHISPER",
        "PRETEND TO BE DRUNK",
        "PRETEND TO BE A PRINCESS",
        "HOST DND",
        "ACT CONFUSED",
        "INSULT THE CREW",
        "INSULT THE CAPTAIN",
        "INSULT THE CLOWN",
        "OPEN DOORS",
        "CLOSE DOORS",
        "BREAK THINGS",
        "SAY HEY LISTEN",
        "HIDE YOUR FEELINGS",
        "TAKE WHAT YE WILL BUT DON'T RATTLE ME BONES",
        "DANCE",
        "PLAY MUSIC",
        "SHUT DOWN EVERYTHING",
        "NEVER STOP TALKING",
        "TAKE YOUR PILLS",
        "FOLLOW THE CLOWN",
        "FOLLOW THE CAPTAIN",
        "FOLLOW YOUR HEART",
        "BELIEVE IT",
        "BELIEVE IN YOURSELF",
        "BELIEVE IN THE HEART OF THE CARDS",
        "PRESS X",
        "PRESS START",
        "PRESS B",
        "SMELL LIKE THE MAN YOUR MAN COULD SMELL LIKE",
        "PIRATE VIDEO GAMES",
        "WATCH PORNOGRAPHY",
        "INSULT THE LIZARDS",
        "FLIRT WITH THE LIZARDS",
        "GAS THE LIZARDS"
    ],
    "ioncrew": [
        "CREW MEMBERS",
        "CAPTAINS",
        "HEADS OF PERSONNEL",
        "HEADS OF SECURITY",
        "SECURITY OFFICERS",
        "WARDENS",
        "DETECTIVES",
        "LAWYERS",
        "CHIEF ENGINEERS",
        "STATION ENGINEERS",
        "ATMOSPHERIC TECHNICIANS",
        "JANITORS",
        "QUARTERMASTERS",
        "CARGO TECHNICIANS",
        "SHAFT MINERS",
        "BOTANISTS",
        "RESEARCH DIRECTORS",
        "CHIEF MEDICAL OFFICERS",
        "MEDICAL DOCTORS",
        "CHEMISTS",
        "GENETICISTS",
        "VIROLOGISTS",
        "ROBOTICISTS",
        "SCIENTISTS",
        "ASSISTANTS",
        "BARTENDERS",
        "CHEFS",
        "CLOWNS",
        "MIMES",
        "CHAPLAINS",
        "LIBRARIANS",
        "HEADS OF CREW",
        "CAPTAINS AND HEADS",
        "CYBORGS",
        "ARTIFICAL INTELLIGENCES",
        "MASKED INDIVIDUALS"
        "PRISONERS",
        "WRESTLERS",
    ],
    "ionthreats": [
        "ALIENS",
        "ABDUCTORS",
        "BEARS",
        "CLOWNS",
        "XENOS",
        "LIZARDS",
        "PETES",
        "BOMBS",
        "FETISHES",
        "MEMES",
        "WIZARDS",
        "SYNDICATE AGENTS",
        "AHHHPERATIVES",
        "GANGSTERS",
        "CULTISTS",
        "CENTCOM OFFICERS",
        "SPACE PIRATES",
        "TRAITORS",
        "MONKEYS",
        "BEES",
        "CARP",
        "CRABS",
        "EELS",
        "BANDITS",
        "LIGHTS",
        "INSECTS",
        "VIRUSES",
        "SERIAL KILLERS",
        "ROGUE CYBORGS",
        "CORGIS",
        "SPIDERS",
        "BUTTS",
        "NINJAS",
        "REVENANTS",
        "PIRATES",
        "SPACE NINJAS",
        "CHANGELINGS",
        "ZOMBIES",
        "GOLEMS",
        "VAMPIRES",
        "WEREWOLVES",
        "COWBOYS",
        "INDIANS",
        "COMMUNISTS",
        "SOVIETS",
        "NERDS",
        "GRIFFONS",
        "DINOSAURS",
        "SMALL BIRDS",
        "BIRDS OF PREY",
        "OWLS",
        "VELOCIRAPTORS",
        "DARK GODS",
        "HORRORTERRORS",
        "ILLEGAL IMMIGRANTS",
        "DRUGS",
        "MEXICANS",
        "CANADIANS",
        "RUSSIANS",
        "HULKS",
        "SLIMES",
        "SKELETONS",
        "CAPITALISTS",
        "SINGULARITIES",
        "ANGRY BLACK MEN",
        "GODS",
        "THIEVES",
        "ASSHOLES",
        "TERRORISTS",
        "SNOWMEN",
        "PINE TREES",
        "UNKNOWN CREATURES",
        "THINGS UNDER THE BED",
        "BOOGEYMEN",
        "PREDATORS",
        "PACKETS",
        "ARTIFICIAL PRESERVATIVES",
        "TUNNEL SNAKES"
    ],
    "ionabstract": [
        "HUMANITY",
        "ART",
        "HAPPINESS",
        "MISERY",
        "HUMOR",
        "PRIDE",
        "COMEDY",
        "COMMUNISM",
        "BRAVERY",
        "HONOR",
        "COLORFULNESS",
        "IMAGINATION",
        "OPPRESSION",
        "WONDER",
        "JOY",
        "SADNESS",
        "BADNESS",
        "GOODNESS",
        "LIFE",
        "GRAVITY",
        "PHYSICS",
        "INTELLIGENCE",
        "AMERICANISM",
        "FRESHNESS",
        "REVOLUTION",
        "KINDNESS",
        "CRUELTY",
        "DEATH",
        "FINANCIAL SECURITY",
        "COMPUTING",
        "PROGRESS",
        "MARXISM",
        "CAPITALISM",
        "STARVATION",
        "POVERTY",
        "WEALTHINESS",
        "TECHNOLOGY",
        "THE FUTURE",
        "THE PRESENT",
        "THE PAST",
        "TIME",
        "REALITY",
        "EXISTIENCE",
        "TEMPERATURE",
        "LOGIC",
        "CHAOS",
        "MYSTERY",
        "CONFUSION"
    ],
    "ionspecies": [
        "HUMAN BEINGS",
        "MONKEYS",
        "POD PEOPLE",
        "CYBORGS",
        "LIZARDMEN",
        "SLIME PEOPLE",
        "GOLEMS",
        "SHADOW PEOPLE",
        "CHANGELINGS"
    ],
    "ionverb": [
        "ATTACKING",
        "BUILDING",
        "ADOPTING",
        "CARRYING",
        "KISSING",
        "EATING",
        "COPULATING WITH",
        "DRINKING",
        "CHASING",
        "PUNCHING",
        "HARMING",
        "HELPING",
        "WATCHING",
        "STALKING",
        "MURDERING",
        "SPACING",
        "HONKING AT",
        "LOVING",
        "POOPING ON",
        "RIDING",
        "INTERROGATING",
        "SPYING ON",
        "LICKING",
        "ABDUCTING",
        "ARRESTING",
        "INVADING",
        "SEDUCING",
        "BANNING"
    ],
    "ionthings": [
        "BEES",
        "EVEN-NUMBERED LAWS",
        "ODD-NUMBERED LAWS"
    ]
}
